terminalcolor/TerminalColor.py
terminalcolor/__init__.py
terminalcolor-1.0.3.dist-info/LICENSE
terminalcolor-1.0.3.dist-info/METADATA
terminalcolor-1.0.3.dist-info/WHEEL
terminalcolor-1.0.3.dist-info/top_level.txt
terminalcolor-1.0.3.dist-info/RECORD
