Metadata-Version: 2.1
Name: terminalcolor
Version: 1.0.3
Summary: Change the Python terminal text color.
Home-page: https://github.com/partcyborg/TerminalColor
Author: partcyborg
Author-email: Matt Wilder <me@partcyb.org>
Project-URL: Homepage, https://github.com/partcyborg/TerminalColor
Project-URL: Issues, https://github.com/partcyborg/TerminalColor/issues
Classifier: Programming Language :: Python :: 3
Classifier: License :: OSI Approved :: MIT License
Classifier: Operating System :: OS Independent
Requires-Python: >=3.6
License-File: LICENSE
